Metadata-Version: 2.4
Name: adafruit-circuitpython-ducky
Version: 1.5.4
Summary: CircuitPython library for running DuckyScript
Author-email: Adafruit Industries <circuitpython@adafruit.com>
License: MIT
Project-URL: Homepage, https://github.com/adafruit/Adafruit_CircuitPython_Ducky.git
Keywords: adafruit,blinka,circuitpython,micropython,ducky,ducky,,rubber,duckyscript
Classifier: Intended Audience :: Developers
Classifier: Topic :: Software Development :: Libraries
Classifier: Topic :: Software Development :: Embedded Systems
Classifier: Topic :: System :: Hardware
Classifier: License :: OSI Approved :: MIT License
Classifier: Programming Language :: Python :: 3
License-File: LICENSE
Requires-Dist: Adafruit-Blinka
Requires-Dist: adafruit-circuitpython-hid
Provides-Extra: optional
Dynamic: license-file
